<Properties StartupConfiguration="{F0172663-F049-4F2B-AF49-DFAEF542D9EB}|Default">
  <MonoDevelop.Ide.ItemProperties.MartaPassengerTraffic.iOS PreferredExecutionTarget="MonoDevelop.IPhone.IPhoneSimulatorTarget.B988DBF6-BE9D-4802-83B5-41978E8FFF5B" />
  <MonoDevelop.Ide.Workbench ActiveDocument="MartaPassengerTraffic/MyPage.xaml">
    <Files>
      <File FileName="MartaPassengerTraffic/App.xaml.cs" Line="10" Column="6" />
      <File FileName="MartaPassengerTraffic/MainPage.xaml.cs" Line="30" Column="46" />
      <File FileName="MartaPassengerTraffic/MainPage.xaml" Line="10" Column="15" />
      <File FileName="MartaPassengerTraffic/MyPage.xaml" Line="6" Column="1" />
      <File FileName="MartaPassengerTraffic/MyPage.xaml.cs" Line="1" Column="1" />
    </Files>
  </MonoDevelop.Ide.Workbench>
  <MonoDevelop.Ide.Workspace ActiveConfiguration="Debug" />
  <MonoDevelop.Ide.DebuggingService.Breakpoints>
    <BreakpointStore />
  </MonoDevelop.Ide.DebuggingService.Breakpoints>
  <MonoDevelop.Ide.ItemProperties.MartaPassengerTraffic.Android PreferredExecutionTarget="Android.Android_Accelerated_Nougat" AndroidDesignerPreferredTheme="Theme.DeviceDefault.NoActionBar.Fullscreen" />
  <MonoDevelop.Ide.DebuggingService.PinnedWatches />
  <MultiItemStartupConfigurations />
</Properties>